citylocations/__init__.py
citylocations/admin.py
citylocations/apps.py
citylocations/models.py
citylocations/tests.py
citylocations/urls.py
citylocations/views.py
citylocations/migrations/__init__.py
citylocations/templates/citylocations/loc_nyc.html
django_cityloc_pkg_charles_battle-0.0.1.dist-info/licenses/LICENSE.txt
django_cityloc_pkg_charles_battle-0.0.1.dist-info/METADATA
django_cityloc_pkg_charles_battle-0.0.1.dist-info/WHEEL
django_cityloc_pkg_charles_battle-0.0.1.dist-info/top_level.txt
django_cityloc_pkg_charles_battle-0.0.1.dist-info/RECORD
