Metadata-Version: 2.4
Name: django_cityloc_pkg_Charles_Battle
Version: 0.0.1
Summary: A Django app about city locations
Author: Author Name
Author-email: authoremail@example.com
Classifier: Environment :: Web Environment
Classifier: Framework :: Django
Classifier: Framework :: Django :: 3.2
Classifier: License :: OSI Approved :: MIT License
Classifier: Operating System :: OS Independent
Classifier: Programming Language :: Python :: 3.9
Requires-Python: >=3.8
License-File: LICENSE.txt
Requires-Dist: Django>=3.2
Dynamic: description
Dynamic: license-file
